cntext/.DS_Store
cntext/__init__.py
cntext/causal.py
cntext/dynamic_model/elmo.py
cntext/font/SourceHanSansCN-Medium.ttf
cntext/hello.py
cntext/io/.DS_Store
cntext/io/__init__.py
cntext/io/data/.DS_Store
cntext/io/data/en_common_LSD2015.yaml
cntext/io/data/en_common_LoughranMcDonald.yaml
cntext/io/data/en_common_NRC.yaml
cntext/io/data/en_common_SentiWS.yaml
cntext/io/data/en_valence_Concreteness.yaml
cntext/io/data/enzh_common_AdvConj.yaml
cntext/io/data/enzh_common_StopWords.yaml
cntext/io/data/zh_common_DUTIR.yaml
cntext/io/data/zh_common_Digitalization.yaml
cntext/io/data/zh_common_EPU.yaml
cntext/io/data/zh_common_FEPU.yaml
cntext/io/data/zh_common_FLS.yaml
cntext/io/data/zh_common_FinacialFormalUnformal.yaml
cntext/io/data/zh_common_FinanceSenti.yaml
cntext/io/data/zh_common_HowNet.yaml
cntext/io/data/zh_common_LoughranMcDonald.yaml
cntext/io/data/zh_common_NTUSD.yaml
cntext/io/data/zh_common_RhetoricalNationalism.yaml
cntext/io/data/zh_common_TsinghuaPraiseDegrade.yaml
cntext/io/data/zh_valence_ChineseEmoBank.yaml
cntext/io/data/zh_valence_SixSemanticDimensionDatabase.yaml
cntext/io/dict.py
cntext/io/file.py
cntext/io/file_副本.py
cntext/io/mda.py
cntext/io/utils.py
cntext/llm.py
cntext/mind.py
cntext/model/.DS_Store
cntext/model/__init__.py
cntext/model/bert.py
cntext/model/build/.DS_Store
cntext/model/build/glove-unix/.DS_Store
cntext/model/build/glove-unix/cooccur
cntext/model/build/glove-unix/glove
cntext/model/build/glove-unix/shuffle
cntext/model/build/glove-unix/vocab_count
cntext/model/build/glove-win_devc_x64/cooccur.exe
cntext/model/build/glove-win_devc_x64/glove.exe
cntext/model/build/glove-win_devc_x64/pthreadVC2.dll
cntext/model/build/glove-win_devc_x64/shuffle.exe
cntext/model/build/glove-win_devc_x64/vocab_count.exe
cntext/model/build/glove-win_devc_x86/cooccur.exe
cntext/model/build/glove-win_devc_x86/glove.exe
cntext/model/build/glove-win_devc_x86/pthreadVC2.dll
cntext/model/build/glove-win_devc_x86/shuffle.exe
cntext-2.2.0.dist-info/LICENSE
cntext-2.2.0.dist-info/METADATA
cntext-2.2.0.dist-info/WHEEL
cntext-2.2.0.dist-info/RECORD
