Metadata-Version: 2.3
Name: cntext
Version: 2.2.0
Summary: Chinese text analysis library, which can perform word frequency statistics, dictionary expansion, sentiment analysis, similarity, readability, co-occurrence analysis, social computing (attitude, prejudice, culture) on texts; Now support Ollama(LLM) analysis
License: MIT
Author: DaDeng
Requires-Python: >=3.8,<4.0
Classifier: License :: OSI Approved :: MIT License
Classifier: Programming Language :: Python :: 3
Classifier: Programming Language :: Python :: 3.8
Classifier: Programming Language :: Python :: 3.9
Classifier: Programming Language :: Python :: 3.10
Classifier: Programming Language :: Python :: 3.11
Classifier: Programming Language :: Python :: 3.12
Classifier: Programming Language :: Python :: 3.13
Requires-Dist: PyMuPDF (>=1.25.4,<2.0.0)
Requires-Dist: PyYAML (>=6.0.2,<7.0.0)
Requires-Dist: aiolimiter (==1.2.1)
Requires-Dist: chardet (>=5.0.0,<6.0.0)
Requires-Dist: contractions (>=0.1.73,<0.2.0)
Requires-Dist: distinctiveness (>=0.14.6,<0.15.0)
Requires-Dist: ftfy (>=6.2.0,<7.0.0)
Requires-Dist: gensim (>=4.2.0,<5.0.0)
Requires-Dist: h5py (>=3.9.0,<4.0.0)
Requires-Dist: instructor (>=1.11.2,<2.0.0)
Requires-Dist: jieba (>=0.42,<0.43)
Requires-Dist: matplotlib (>=3.6.0,<4.0.0)
Requires-Dist: nest-asyncio (>=1.6.0,<2.0.0)
Requires-Dist: networkx (>=3.2,<4.0)
Requires-Dist: nltk (>=3.8,<4.0)
Requires-Dist: numpy (>=1.26.4,<2.0.0)
Requires-Dist: ollama (>=0.2.1,<0.3.0)
Requires-Dist: openai (>=1.107.0,<2.0.0)
Requires-Dist: opencc-python-reimplemented (>=0.1.6,<0.2.0)
Requires-Dist: pandas (>=2.2.0,<3.0.0)
Requires-Dist: pydantic (>=2.11.7,<3.0.0)
Requires-Dist: pyecharts (==2.0.0)
Requires-Dist: python-docx (>=1.1.2,<2.0.0)
Requires-Dist: scikit-learn (>=1.5.0,<2.0.0)
Requires-Dist: scipy (>=1.12.0,<2.0.0)
Requires-Dist: tqdm (>=4.66.4,<5.0.0)
